analysis_project_root/__init__.py
analysis_project_root/_version.py
analysis_project_root/pathmagic.py
analysis_project_root-0.1.0.dist-info/LICENSE
analysis_project_root-0.1.0.dist-info/WHEEL
analysis_project_root-0.1.0.dist-info/METADATA
analysis_project_root-0.1.0.dist-info/RECORD
