Metadata-Version: 2.1
Name: analysis_project_root
Version: 0.1.0
Summary: analysis_project_root - change the root in an analysis project.
Home-page: https://github.com/richardangell/analysis-project-root
Author: Richard Angell
Author-email: richardangell37@gmail.com
Requires-Python: >=3.7
Classifier: Programming Language :: Python :: 3
Classifier: License :: OSI Approved :: BSD License
Classifier: Operating System :: OS Independent
Requires-Dist: pre-commit==2.19.0 ; extra == "test"
Requires-Dist: pytest==7.1.2 ; extra == "test"
Project-URL: PyPI, https://pypi.org/project/analysis-project-root/
Provides-Extra: test
